needle/__init__.py
needle/utils.py
needle/v1/__init__.py
needle/v1/collections/__init__.py
needle/v1/collections/files.py
needle/v1/files/__init__.py
needle/v1/models.py
needle_python-0.6.0.dist-info/LICENSE
needle_python-0.6.0.dist-info/METADATA
needle_python-0.6.0.dist-info/WHEEL
needle_python-0.6.0.dist-info/RECORD
