Metadata-Version: 2.3
Name: needle-python
Version: 0.6.0
Summary: Needle client library for Python
License: MIT
Keywords: needle,api,retrieval-augmented generation,rag,information-retrieval,artificial intelligence,ai
Author: Onur Eken
Author-email: m.onureken@gmail.com
Requires-Python: >=3.8,<4.0
Classifier: Development Status :: 4 - Beta
Classifier: Intended Audience :: Developers
Classifier: License :: OSI Approved :: MIT License
Classifier: Operating System :: OS Independent
Classifier: Programming Language :: Python :: 3
Classifier: Programming Language :: Python :: 3.8
Classifier: Programming Language :: Python :: 3.9
Classifier: Programming Language :: Python :: 3.10
Classifier: Programming Language :: Python :: 3.11
Classifier: Programming Language :: Python :: 3.12
Classifier: Programming Language :: Python :: 3.13
Classifier: Topic :: Scientific/Engineering :: Artificial Intelligence
Classifier: Topic :: Software Development :: Libraries :: Python Modules
Requires-Dist: requests (>=2.32.3,<3.0.0)
Project-URL: documentation, https://docs.needle.app
Project-URL: homepage, https://needle.app
Project-URL: issues, https://github.com/oeken/needle-python/issues
Project-URL: repository, https://github.com/oeken/needle-python
